exceptionite/Action.py
exceptionite/Block.py
exceptionite/Handler.py
exceptionite/StackTrace.py
exceptionite/Tab.py
exceptionite/__init__.py
exceptionite/exceptions.py
exceptionite/options.py
exceptionite/solutions.py
exceptionite/version.py
exceptionite/assets/App.vue
exceptionite/assets/Exceptionite.js
exceptionite/assets/app.css
exceptionite/assets/app.js
exceptionite/assets/editorUrl.js
exceptionite/assets/components/Alert.vue
exceptionite/assets/components/AppButton.vue
exceptionite/assets/components/Badge.vue
exceptionite/assets/components/BaseActionDialog.vue
exceptionite/assets/components/ContextMenu.vue
exceptionite/assets/components/CopyButton.vue
exceptionite/assets/components/Exception.vue
exceptionite/assets/components/FirstSolution.vue
exceptionite/assets/components/Frame.vue
exceptionite/assets/components/FrameVars.vue
exceptionite/assets/components/KeyValItem.vue
exceptionite/assets/components/KeyValList.vue
exceptionite/assets/components/Navbar.vue
exceptionite/assets/components/NoSolution.vue
exceptionite/assets/components/Pulse.vue
exceptionite/assets/components/ShareDialog.vue
exceptionite/assets/components/ShareSelector.vue
exceptionite/assets/components/Sponsor.vue
exceptionite/assets/components/Stack.vue
exceptionite/assets/components/Switch.vue
exceptionite/assets/components/blocks/Basic.vue
exceptionite/assets/components/blocks/PackagesUpdates.vue
exceptionite/assets/components/blocks/PossibleSolutions.vue
exceptionite/assets/components/blocks/StackOverflow.vue
exceptionite/assets/components/blocks/index.js
exceptionite/assets/components/tabs/Basic.vue
exceptionite/assets/components/tabs/Dumps.vue
exceptionite/assets/components/tabs/index.js
exceptionite/assets/themes/atom-one-dark.css
exceptionite/assets/themes/atom-one-light.css
exceptionite/blocks/Environment.py
exceptionite/blocks/Git.py
exceptionite/blocks/Packages.py
exceptionite/blocks/PackagesUpdates.py
exceptionite/blocks/PossibleSolutions.py
exceptionite/blocks/StackOverflow.py
exceptionite-3.0.0.dist-info/LICENSE
exceptionite-3.0.0.dist-info/METADATA
exceptionite-3.0.0.dist-info/WHEEL
exceptionite-3.0.0.dist-info/top_level.txt
exceptionite-3.0.0.dist-info/RECORD
