Metadata-Version: 2.1
Name: exceptionite
Version: 3.0.0
Summary: Exception Handling Made Easy
Home-page: https://github.com/masoniteframework/exceptionite
Author: The Masonite Community
Author-email: joe@masoniteproject.com
License: MIT license
Keywords: Masonite,Python,Development,Framework
Platform: UNKNOWN
Classifier: Development Status :: 5 - Production/Stable
Classifier: Intended Audience :: Developers
Classifier: Topic :: Software Development :: Build Tools
Classifier: Environment :: Web Environment
Classifier: License :: OSI Approved :: MIT License
Classifier: Operating System :: OS Independent
Classifier: Programming Language :: Python :: 3.8
Classifier: Programming Language :: Python :: 3.9
Classifier: Programming Language :: Python :: 3.10
Classifier: Programming Language :: Python :: 3.11
Classifier: Programming Language :: Python :: 3.12
Classifier: Topic :: Internet :: WWW/HTTP
Classifier: Topic :: Internet :: WWW/HTTP :: Dynamic Content
Classifier: Topic :: Internet :: WWW/HTTP :: WSGI
Classifier: Topic :: Software Development :: Libraries :: Application Frameworks
Classifier: Topic :: Software Development :: Libraries :: Python Modules
Classifier: Framework :: Masonite
License-File: LICENSE
Requires-Dist: jinja2
Requires-Dist: requests
Requires-Dist: colorama
Requires-Dist: dotty-dict
Requires-Dist: typing-extensions
Requires-Dist: mock
Provides-Extra: test
Requires-Dist: black ; extra == 'test'
Requires-Dist: flake8 ; extra == 'test'
Requires-Dist: coverage ; extra == 'test'
Requires-Dist: pytest ; extra == 'test'
Requires-Dist: pytest-cov ; extra == 'test'
Requires-Dist: twine (>=1.5.0) ; extra == 'test'
Requires-Dist: wheel ; extra == 'test'
